excel_sbol_utils/__init__.py
excel_sbol_utils/helpers.py
excel_sbol_utils/library2.py
excel_sbol_utils/library3.py
excel_sbol_utils/temp.py
excel_sbol_utils/test.py
excel_sbol_utils-1.0.49.dist-info/METADATA
excel_sbol_utils-1.0.49.dist-info/WHEEL
excel_sbol_utils-1.0.49.dist-info/top_level.txt
excel_sbol_utils-1.0.49.dist-info/RECORD
