Metadata-Version: 2.4
Name: excel-sbol-utils
Version: 1.0.49
Summary: help convert excel resources into sbol
Home-page: https://github.com/SynBioDex/Excel-utilities/
Maintainer: Jet Mante
Maintainer-email: jet.mante@colorado.edu
License: BSD 3-clause
Requires-Dist: sbol3>=1.0.1
Dynamic: description
Dynamic: home-page
Dynamic: license
Dynamic: maintainer
Dynamic: maintainer-email
Dynamic: requires-dist
Dynamic: summary
